<?xml version="1.0" encoding="UTF-8"?>
<addon
    id="plugin.video.category5"
    name="Category5.TV"
    version="1.0.12"
    provider-name="Category5 TV Network">
    <requires>
        <import addon="xbmc.python" version="2.1.0" />
    </requires>
    <extension point="xbmc.python.pluginsource" library="default.py">
        <provides>video</provides>
        <provides>audio</provides>
    </extension>
    <extension point="xbmc.addon.metadata">
        <summary lang="en">Category5 Add On</summary>
        <description lang="en">Watch shows from the Category5 TV Network, including Category5 Technology TV.</description>
        <disclaimer lang="en">Please visit http://www.category5.tv/ for more information.</disclaimer>
        <license>GNU GENERAL PUBLIC LICENSE. Version 2, June 1991</license>
        <website>http://www.category5.tv</website>
        <source>https://github.com/Cat5TV/plugin.video.category5</source>
        <platform>all</platform>
        <language>en</language>
    </extension>
</addon>
